CHANGES.rst
LICENSE
MANIFEST.in
README.rst
requirements.txt
setup.cfg
setup.py
arouteserver.egg-info/PKG-INFO
arouteserver.egg-info/SOURCES.txt
arouteserver.egg-info/dependency_links.txt
arouteserver.egg-info/namespace_packages.txt
arouteserver.egg-info/requires.txt
arouteserver.egg-info/top_level.txt
pierky/__init__.py
pierky/arouteserver/__init__.py
pierky/arouteserver/arin_db_dump.py
pierky/arouteserver/ask.py
pierky/arouteserver/builder.py
pierky/arouteserver/cached_objects.py
pierky/arouteserver/errors.py
pierky/arouteserver/euro_ix.py
pierky/arouteserver/ipaddresses.py
pierky/arouteserver/irrdb.py
pierky/arouteserver/last_version.py
pierky/arouteserver/peering_db.py
pierky/arouteserver/registro_br_db_dump.py
pierky/arouteserver/reject_reasons.py
pierky/arouteserver/resources.py
pierky/arouteserver/ripe_rpki_cache.py
pierky/arouteserver/version.py
pierky/arouteserver/commands/__init__.py
pierky/arouteserver/commands/base.py
pierky/arouteserver/commands/check_config.py
pierky/arouteserver/commands/check_new_release.py
pierky/arouteserver/commands/clients_from_euroix.py
pierky/arouteserver/commands/clients_from_peeringdb.py
pierky/arouteserver/commands/configure.py
pierky/arouteserver/commands/init_scenario.py
pierky/arouteserver/commands/ixf_member_list_from_clients.py
pierky/arouteserver/commands/setup.py
pierky/arouteserver/commands/setup_templates.py
pierky/arouteserver/commands/show_config.py
pierky/arouteserver/commands/tpl_rendering.py
pierky/arouteserver/commands/verify_templates.py
pierky/arouteserver/config/__init__.py
pierky/arouteserver/config/asns.py
pierky/arouteserver/config/base.py
pierky/arouteserver/config/bogons.py
pierky/arouteserver/config/clients.py
pierky/arouteserver/config/general.py
pierky/arouteserver/config/program.py
pierky/arouteserver/config/validators.py
pierky/arouteserver/config.d/arouteserver.yml
pierky/arouteserver/config.d/bogons.yml
pierky/arouteserver/config.d/clients.yml
pierky/arouteserver/config.d/general.distrib.yml
pierky/arouteserver/config.d/log.ini
pierky/arouteserver/config.d/rtt_getter.sh
pierky/arouteserver/enrichers/__init__.py
pierky/arouteserver/enrichers/arin_db_dump.py
pierky/arouteserver/enrichers/base.py
