Metadata-Version: 1.2
Name: arouteserver
Version: 1.15.0
Summary: A Python tool to automatically build (and test) configurations for BGP route servers.
Home-page: https://github.com/pierky/arouteserver
Author: Pier Carlo Chiodi
Author-email: pierky@pierky.com
Maintainer: Pier Carlo Chiodi
Maintainer-email: pierky@pierky.com
License: GPLv3
Download-URL: https://github.com/pierky/arouteserver
Keywords: BGP,Route server,BIRD,IP Routing,OpenBGPD,IXP,IX,Internet Exchange
Platform: UNKNOWN
Classifier: Development Status :: 5 - Production/Stable
Classifier: Environment :: Console
Classifier: Intended Audience :: Information Technology
Classifier: Intended Audience :: System Administrators
Classifier: Intended Audience :: Telecommunications Industry
Classifier: License :: OSI Approved :: GNU General Public License v3 (GPLv3)
Classifier: Operating System :: POSIX
Classifier: Operating System :: Unix
Classifier: Programming Language :: Python
Classifier: Programming Language :: Python :: 3.6
Classifier: Programming Language :: Python :: 3.8
Classifier: Programming Language :: Python :: 3.9
Classifier: Topic :: Internet :: WWW/HTTP
Classifier: Topic :: System :: Networking
